appcensus/dynamic_repos/__init__.py
appcensus/dynamic_repos/auth.py
appcensus/dynamic_repos/commands.py
appcensus/dynamic_repos/models.py
appcensus/dynamic_repos/plugin.py
appcensus/dynamic_repos/pool_manager.py
appcensus/dynamic_repos/repo_collector.py
appcensus_dynamic_repos-2.1.117.dist-info/METADATA
appcensus_dynamic_repos-2.1.117.dist-info/WHEEL
appcensus_dynamic_repos-2.1.117.dist-info/entry_points.txt
appcensus_dynamic_repos-2.1.117.dist-info/RECORD
