Metadata-Version: 2.1
Name: appcensus.dynamic_repos
Version: 2.1.117
Summary: Dynamic Poetry Repositories for AppCensus
License: (c) 2022 App Census - All Rights Reserved
Author: AppCensus
Author-email: engineering@appcensus.io
Requires-Python: >=3.10.0,<4.0.0
Classifier: License :: Other/Proprietary License
Classifier: Programming Language :: Python :: 3
Classifier: Programming Language :: Python :: 3.10
Classifier: Programming Language :: Python :: 3.11
Classifier: Programming Language :: Python :: 3.12
Requires-Dist: boto3 (>=1.26.0,<2.0.0)
Requires-Dist: botocore (>=1.29.0,<2.0.0)
Requires-Dist: cryptography (>=38.0.0)
Requires-Dist: poetry (>=2.1,<2.2)
Requires-Dist: poetry-core (>=1.9)
Requires-Dist: pydantic (>=2.0.1,<3.0.0)
Requires-Dist: pytz (>=2022.5,<2023.0)
Requires-Dist: tomli (>=2.0.1,<3.0.0)
Requires-Dist: tomlkit (>=0.11.0,<0.12.0)
